mkdocs_annexes_integration/__init__.py
mkdocs_annexes_integration/plugin.py
mkdocs_annexes_integration-0.1.7.dist-info/METADATA
mkdocs_annexes_integration-0.1.7.dist-info/WHEEL
mkdocs_annexes_integration-0.1.7.dist-info/entry_points.txt
mkdocs_annexes_integration-0.1.7.dist-info/top_level.txt
mkdocs_annexes_integration-0.1.7.dist-info/RECORD
